Metadata-Version: 2.1
Name: bru
Version: 0.0.2
Summary: A package for all things Bru!
Home-page: https://github.com/adityasaky/bru
Author: Aditya Saky
Author-email: asy278@nyu.edu
License: UNKNOWN
Platform: UNKNOWN
Classifier: Programming Language :: Python :: 3
Classifier: License :: OSI Approved :: GNU General Public License (GPL)
Classifier: Operating System :: OS Independent
Requires-Python: >=3.6
License-File: LICENSE
